ehte/__init__.py
ehte/eHTE.py
ehte/original/eHTE-0.py
ehte-1.0.1.dist-info/LICENSE
ehte-1.0.1.dist-info/METADATA
ehte-1.0.1.dist-info/WHEEL
ehte-1.0.1.dist-info/top_level.txt
ehte-1.0.1.dist-info/RECORD
